Metadata-Version: 2.1
Name: cmaster
Version: 0.0.20230622.1
Summary: Comms master
Home-page: http://github.com/acceso/cmaster
Author: Jose Sanchez
License: GNU Affero General Public License v3
Classifier: Development Status :: 2 - Pre-Alpha
Classifier: Environment :: Console
Classifier: Intended Audience :: Developers
Classifier: License :: OSI Approved :: GNU Affero General Public License v3
Classifier: Operating System :: OS Independent
Classifier: Programming Language :: Python :: 3 :: Only
License-File: LICENSE
